{
	"name": "master_pipeline",
	"properties": {
		"activities": [
			{
				"name": "Data flow emp",
				"type": "ExecuteDataFlow",
				"dependsOn": [],
				"policy": {
					"timeout": "0.12:00:00",
					"retry": 0,
					"retryIntervalInSeconds": 30,
					"secureOutput": false,
					"secureInput": false
				},
				"userProperties": [],
				"typeProperties": {
					"dataflow": {
						"referenceName": "source to sink Emp Master dataflow",
						"type": "DataFlowReference"
					},
					"staging": {
						"linkedService": {
							"referenceName": "ls_adls",
							"type": "LinkedServiceReference"
						},
						"folderPath": "adlsnycpayroll-iyeoluwa-akinrinolai/dirstaging"
					},
					"compute": {
						"coreCount": 8,
						"computeType": "General"
					},
					"traceLevel": "Fine"
				}
			},
			{
				"name": "Data flow title",
				"type": "ExecuteDataFlow",
				"dependsOn": [],
				"policy": {
					"timeout": "0.12:00:00",
					"retry": 0,
					"retryIntervalInSeconds": 30,
					"secureOutput": false,
					"secureInput": false
				},
				"userProperties": [],
				"typeProperties": {
					"dataflow": {
						"referenceName": "source to sink title master",
						"type": "DataFlowReference"
					},
					"staging": {
						"linkedService": {
							"referenceName": "ls_adls",
							"type": "LinkedServiceReference"
						},
						"folderPath": "adlsnycpayroll-iyeoluwa-akinrinolai/dirstaging"
					},
					"compute": {
						"coreCount": 8,
						"computeType": "General"
					},
					"traceLevel": "Fine"
				}
			},
			{
				"name": "Data flow agency",
				"type": "ExecuteDataFlow",
				"dependsOn": [],
				"policy": {
					"timeout": "0.12:00:00",
					"retry": 0,
					"retryIntervalInSeconds": 30,
					"secureOutput": false,
					"secureInput": false
				},
				"userProperties": [],
				"typeProperties": {
					"dataflow": {
						"referenceName": "source to sink agency master dataflow",
						"type": "DataFlowReference"
					},
					"staging": {
						"linkedService": {
							"referenceName": "ls_adls",
							"type": "LinkedServiceReference"
						},
						"folderPath": "adlsnycpayroll-iyeoluwa-akinrinolai/dirstaging"
					},
					"compute": {
						"coreCount": 8,
						"computeType": "General"
					},
					"traceLevel": "Fine"
				}
			},
			{
				"name": "Data flow nyc db to synapse",
				"type": "ExecuteDataFlow",
				"dependsOn": [
					{
						"activity": "Data flow emp",
						"dependencyConditions": [
							"Succeeded"
						]
					},
					{
						"activity": "Data flow title",
						"dependencyConditions": [
							"Succeeded"
						]
					},
					{
						"activity": "Data flow agency",
						"dependencyConditions": [
							"Succeeded"
						]
					}
				],
				"policy": {
					"timeout": "0.12:00:00",
					"retry": 0,
					"retryIntervalInSeconds": 30,
					"secureOutput": false,
					"secureInput": false
				},
				"userProperties": [],
				"typeProperties": {
					"dataflow": {
						"referenceName": "nyc db source to sink",
						"type": "DataFlowReference"
					},
					"staging": {
						"linkedService": {
							"referenceName": "ls_adls",
							"type": "LinkedServiceReference"
						},
						"folderPath": "adlsnycpayroll-iyeoluwa-akinrinolai/dirstaging"
					},
					"compute": {
						"coreCount": 8,
						"computeType": "General"
					},
					"traceLevel": "Fine"
				}
			}
		],
		"annotations": [],
		"lastPublishTime": "2023-07-26T00:24:39Z"
	},
	"type": "Microsoft.DataFactory/factories/pipelines"
}